sentrev/__init__.py
sentrev/evaluator.py
sentrev/utils.py
sentrev-1.0.1.dist-info/LICENSE
sentrev-1.0.1.dist-info/METADATA
sentrev-1.0.1.dist-info/WHEEL
sentrev-1.0.1.dist-info/top_level.txt
sentrev-1.0.1.dist-info/RECORD
