Metadata-Version: 2.2
Name: sentrev
Version: 1.0.1
Summary: SenTrEv - Simple customizable evaluation for dense and sparse retrieval performance on your text documents
Author-email: "Clelia (Astra) Bertelli" <astraberte9@gmail.com>
Project-URL: Homepage, https://github.com/AstraBert/SenTrEv
Project-URL: Issues, https://github.com/AstraBert/SenTrEv/issues
Classifier: Programming Language :: Python :: 3
Classifier: License :: OSI Approved :: MIT License
Classifier: Operating System :: OS Independent
Requires-Python: >=3.10
License-File: LICENSE
Requires-Dist: sentence_transformers==3.0.1
Requires-Dist: qdrant_client==1.10.1
Requires-Dist: pypdf==4.3.1
Requires-Dist: langchain
Requires-Dist: langchain_core
Requires-Dist: langchain_community
Requires-Dist: langchain_text_splitters
Requires-Dist: matplotlib
Requires-Dist: codecarbon
Requires-Dist: pandas
Requires-Dist: fastembed
Requires-Dist: pdfitdown
